{
    "Status": 0,
    "Message": "Success",
    "Data": [
        {
            "ChartOfAccountID": "01102",
            "CompanyID": "011",
            "GroupAccountID": "01000001",
            "AccountNo": "1101939",
            "Description": "Vending Mesin Pesona Depok",
            "ParentID": "011",
            "IsChildest": true,
            "IsBank": true,
            "Type": "3",
            "IsDeleted": false,
            "ModifiedDate": "2022-01-03T00:00:00"
        },
        {
            "ChartOfAccountID": "01103",
            "CompanyID": "011",
            "GroupAccountID": "01000001",
            "AccountNo": "1101940",
            "Description": "Vending Mesin GGP",
            "ParentID": "011",
            "IsChildest": true,
            "IsBank": true,
            "Type": "3",
            "IsDeleted": false,
            "ModifiedDate": "2022-01-03T00:00:00"
        },
        {
            "ChartOfAccountID": "01104",
            "CompanyID": "011",
            "GroupAccountID": "01000001",
            "AccountNo": "1101941",
            "Description": "Vending Mesin Season City",
            "ParentID": "011",
            "IsChildest": true,
            "IsBank": true,
            "Type": "3",
            "IsDeleted": false,
            "ModifiedDate": "2022-01-03T00:00:00"
        },
        {
            "ChartOfAccountID": "01105",
            "CompanyID": "011",
            "GroupAccountID": "01000001",
            "AccountNo": "1101942",
            "Description": "Vending Mesin SKA Pekan Baru",
            "ParentID": "011",
            "IsChildest": true,
            "IsBank": true,
            "Type": "3",
            "IsDeleted": false,
            "ModifiedDate": "2022-01-03T00:00:00"
        },
        {
            "ChartOfAccountID": "01106",
            "CompanyID": "011",
            "GroupAccountID": "01000001",
            "AccountNo": "1101943",
            "Description": "Vending Mesin Citraland",
            "ParentID": "011",
            "IsChildest": true,
            "IsBank": true,
            "Type": "3",
            "IsDeleted": false,
            "ModifiedDate": "2022-01-03T00:00:00"
        },
        {
            "ChartOfAccountID": "01107",
            "CompanyID": "011",
            "GroupAccountID": "01000001",
            "AccountNo": "1101944",
            "Description": "Vending Mesin Bassura City",
            "ParentID": "011",
            "IsChildest": true,
            "IsBank": true,
            "Type": "3",
            "IsDeleted": false,
            "ModifiedDate": "2022-01-03T00:00:00"
        },
        {
            "ChartOfAccountID": "01108",
            "CompanyID": "011",
            "GroupAccountID": "01000001",
            "AccountNo": "1101945",
            "Description": "Vending Mesin Bandung Indah Plaza",
            "ParentID": "011",
            "IsChildest": true,
            "IsBank": true,
            "Type": "3",
            "IsDeleted": false,
            "ModifiedDate": "2022-01-03T00:00:00"
        },
        {
            "ChartOfAccountID": "01109",
            "CompanyID": "011",
            "GroupAccountID": "01000001",
            "AccountNo": "1101946",
            "Description": "Vending Mesin Hartono Yogya",
            "ParentID": "011",
            "IsChildest": true,
            "IsBank": true,
            "Type": "3",
            "IsDeleted": false,
            "ModifiedDate": "2022-01-03T00:00:00"
        },
        {
            "ChartOfAccountID": "01110",
            "CompanyID": "011",
            "GroupAccountID": "01000001",
            "AccountNo": "1101947",
            "Description": "Vending Mesin Medan Fair",
            "ParentID": "011",
            "IsChildest": true,
            "IsBank": true,
            "Type": "3",
            "IsDeleted": false,
            "ModifiedDate": "2022-01-03T00:00:00"
        },
        {
            "ChartOfAccountID": "01111",
            "CompanyID": "011",
            "GroupAccountID": "01000001",
            "AccountNo": "1101948",
            "Description": "Vending Mesin TSM Bandung",
            "ParentID": "011",
            "IsChildest": true,
            "IsBank": true,
            "Type": "3",
            "IsDeleted": false,
            "ModifiedDate": "2022-01-03T00:00:00"
        },
        {
            "ChartOfAccountID": "01112",
            "CompanyID": "011",
            "GroupAccountID": "01000001",
            "AccountNo": "1101949",
            "Description": "Vending Mesin TSM Cibubur",
            "ParentID": "011",
            "IsChildest": true,
            "IsBank": true,
            "Type": "3",
            "IsDeleted": false,
            "ModifiedDate": "2022-01-03T00:00:00"
        },
        {
            "ChartOfAccountID": "01113",
            "CompanyID": "011",
            "GroupAccountID": "01000001",
            "AccountNo": "1101950",
            "Description": "Vending Mesin Panakukang Makassar",
            "ParentID": "011",
            "IsChildest": true,
            "IsBank": true,
            "Type": "3",
            "IsDeleted": false,
            "ModifiedDate": "2022-01-03T00:00:00"
        },
        {
            "ChartOfAccountID": "01114",
            "CompanyID": "011",
            "GroupAccountID": "01000001",
            "AccountNo": "1101951",
            "Description": "Vending Mesin TSM Makassar",
            "ParentID": "011",
            "IsChildest": true,
            "IsBank": true,
            "Type": "3",
            "IsDeleted": false,
            "ModifiedDate": "2022-01-03T00:00:00"
        },
        {
            "ChartOfAccountID": "01115",
            "CompanyID": "011",
            "GroupAccountID": "01000001",
            "AccountNo": "1101952",
            "Description": "Vending Mesin Cilegon Center Mall",
            "ParentID": "011",
            "IsChildest": true,
            "IsBank": true,
            "Type": "3",
            "IsDeleted": false,
            "ModifiedDate": "2022-01-03T00:00:00"
        },
        {
            "ChartOfAccountID": "01116",
            "CompanyID": "011",
            "GroupAccountID": "01000001",
            "AccountNo": "1101953",
            "Description": "Vending Mesin Mal Taman Anggrek",
            "ParentID": "011",
            "IsChildest": true,
            "IsBank": true,
            "Type": "3",
            "IsDeleted": false,
            "ModifiedDate": "2022-01-03T00:00:00"
        },
        {
            "ChartOfAccountID": "01117",
            "CompanyID": "011",
            "GroupAccountID": "01000001",
            "AccountNo": "1101954",
            "Description": "Vending Mesin Duta Mall Banjarmasin",
            "ParentID": "011",
            "IsChildest": true,
            "IsBank": true,
            "Type": "3",
            "IsDeleted": false,
            "ModifiedDate": "2022-01-03T00:00:00"
        },
        {
            "ChartOfAccountID": "01118",
            "CompanyID": "011",
            "GroupAccountID": "01000001",
            "AccountNo": "1101955",
            "Description": "Vending Mesin Green Pramuka",
            "ParentID": "011",
            "IsChildest": true,
            "IsBank": true,
            "Type": "3",
            "IsDeleted": false,
            "ModifiedDate": "2022-01-03T00:00:00"
        },
        {
            "ChartOfAccountID": "01119",
            "CompanyID": "011",
            "GroupAccountID": "01000001",
            "AccountNo": "1101956",
            "Description": "Vending Mesin LWAS",
            "ParentID": "011",
            "IsChildest": true,
            "IsBank": true,
            "Type": "3",
            "IsDeleted": false,
            "ModifiedDate": "2022-01-03T00:00:00"
        },
        {
            "ChartOfAccountID": "01120",
            "CompanyID": "011",
            "GroupAccountID": "01000001",
            "AccountNo": "1101957",
            "Description": "Vending Mesin Paragon Semarang",
            "ParentID": "011",
            "IsChildest": true,
            "IsBank": true,
            "Type": "3",
            "IsDeleted": false,
            "ModifiedDate": "2022-01-03T00:00:00"
        },
        {
            "ChartOfAccountID": "01121",
            "CompanyID": "011",
            "GroupAccountID": "01000001",
            "AccountNo": "1101958",
            "Description": "Vending Mesin Central Park",
            "ParentID": "011",
            "IsChildest": true,
            "IsBank": true,
            "Type": "3",
            "IsDeleted": false,
            "ModifiedDate": "2022-01-03T00:00:00"
        },
        {
            "ChartOfAccountID": "01122",
            "CompanyID": "011",
            "GroupAccountID": "01000001",
            "AccountNo": "1101959",
            "Description": "Vending Mesin Grand Batam",
            "ParentID": "011",
            "IsChildest": true,
            "IsBank": true,
            "Type": "3",
            "IsDeleted": false,
            "ModifiedDate": "2022-01-03T00:00:00"
        },
        {
            "ChartOfAccountID": "01123",
            "CompanyID": "011",
            "GroupAccountID": "01000001",
            "AccountNo": "1101960",
            "Description": "Vending Mesin Deli Park Medan",
            "ParentID": "011",
            "IsChildest": true,
            "IsBank": true,
            "Type": "3",
            "IsDeleted": false,
            "ModifiedDate": "2022-01-03T00:00:00"
        },
        {
            "ChartOfAccountID": "01124",
            "CompanyID": "011",
            "GroupAccountID": "01000001",
            "AccountNo": "1101961",
            "Description": "Vending Mesin Ixobox Home Service",
            "ParentID": "011",
            "IsChildest": true,
            "IsBank": true,
            "Type": "3",
            "IsDeleted": false,
            "ModifiedDate": "2022-01-03T00:00:00"
        },
        {
            "ChartOfAccountID": "01125",
            "CompanyID": "011",
            "GroupAccountID": "01000001",
            "AccountNo": "1101962",
            "Description": "Vending Mesin Green Sedayu Mall",
            "ParentID": "011",
            "IsChildest": true,
            "IsBank": true,
            "Type": "3",
            "IsDeleted": false,
            "ModifiedDate": "2022-01-03T00:00:00"
        },
        {
            "ChartOfAccountID": "01126",
            "CompanyID": "011",
            "GroupAccountID": "01000001",
            "AccountNo": "1101963",
            "Description": "Vending Mesin Royal Plaza Surabaya",
            "ParentID": "011",
            "IsChildest": true,
            "IsBank": true,
            "Type": "3",
            "IsDeleted": false,
            "ModifiedDate": "2022-01-03T00:00:00"
        },
        {
            "ChartOfAccountID": "01127",
            "CompanyID": "011",
            "GroupAccountID": "01000001",
            "AccountNo": "1101964",
            "Description": "Vending Mesin Kota Kasablanka",
            "ParentID": "011",
            "IsChildest": true,
            "IsBank": true,
            "Type": "3",
            "IsDeleted": false,
            "ModifiedDate": "2022-01-03T00:00:00"
        },
        {
            "ChartOfAccountID": "01128",
            "CompanyID": "011",
            "GroupAccountID": "01000001",
            "AccountNo": "1101965",
            "Description": "Vending Mesin Tang City",
            "ParentID": "011",
            "IsChildest": true,
            "IsBank": true,
            "Type": "3",
            "IsDeleted": false,
            "ModifiedDate": "2022-01-03T00:00:00"
        },
        {
            "ChartOfAccountID": "01388",
            "CompanyID": "011",
            "GroupAccountID": "01000001",
            "AccountNo": "1101966",
            "Description": "Vending Mesin Citos",
            "ParentID": "011",
            "IsChildest": true,
            "IsBank": false,
            "Type": "3",
            "IsDeleted": false,
            "ModifiedDate": "2022-02-02T11:50:17.16"
        },
        {
            "ChartOfAccountID": "01131",
            "CompanyID": "011",
            "GroupAccountID": "01000001",
            "AccountNo": "1102001",
            "Description": "BCA IMA - 6840308608",
            "ParentID": "01130",
            "IsChildest": true,
            "IsBank": true,
            "Type": "3",
            "IsDeleted": false,
            "ModifiedDate": "2022-01-03T00:00:00"
        },
        {
            "ChartOfAccountID": "01132",
            "CompanyID": "011",
            "GroupAccountID": "01000001",
            "AccountNo": "1102002",
            "Description": "BCA IMA - 6840800511",
            "ParentID": "01130",
            "IsChildest": true,
            "IsBank": true,
            "Type": "3",
            "IsDeleted": false,
            "ModifiedDate": "2022-01-03T00:00:00"
        },
        {
            "ChartOfAccountID": "01133",
            "CompanyID": "011",
            "GroupAccountID": "01000001",
            "AccountNo": "1102003",
            "Description": "BNI IMA - 8898820159",
            "ParentID": "01130",
            "IsChildest": true,
            "IsBank": true,
            "Type": "3",
            "IsDeleted": false,
            "ModifiedDate": "2022-01-03T00:00:00"
        },
        {
            "ChartOfAccountID": "01134",
            "CompanyID": "011",
            "GroupAccountID": "01000001",
            "AccountNo": "1102004",
            "Description": "BCA IMS -6840345473",
            "ParentID": "01130",
            "IsChildest": true,
            "IsBank": true,
            "Type": "3",
            "IsDeleted": false,
            "ModifiedDate": "2022-01-03T00:00:00"
        },
        {
            "ChartOfAccountID": "01135",
            "CompanyID": "011",
            "GroupAccountID": "01000001",
            "AccountNo": "1102005",
            "Description": "Mandiri - 1180010448362",
            "ParentID": "01130",
            "IsChildest": true,
            "IsBank": true,
            "Type": "3",
            "IsDeleted": false,
            "ModifiedDate": "2022-01-03T00:00:00"
        },
        {
            "ChartOfAccountID": "01136",
            "CompanyID": "011",
            "GroupAccountID": "01000001",
            "AccountNo": "1102006",
            "Description": "Mandiri - 1180010448354",
            "ParentID": "01130",
            "IsChildest": true,
            "IsBank": true,
            "Type": "3",
            "IsDeleted": false,
            "ModifiedDate": "2022-01-03T00:00:00"
        },
        {
            "ChartOfAccountID": "01137",
            "CompanyID": "011",
            "GroupAccountID": "01000001",
            "AccountNo": "1102007",
            "Description": "BNI - 8898820171",
            "ParentID": "01130",
            "IsChildest": true,
            "IsBank": true,
            "Type": "3",
            "IsDeleted": false,
            "ModifiedDate": "2022-01-03T00:00:00"
        },
        {
            "ChartOfAccountID": "01138",
            "CompanyID": "011",
            "GroupAccountID": "01000001",
            "AccountNo": "1102008",
            "Description": "BNI - 8898820217",
            "ParentID": "01130",
            "IsChildest": true,
            "IsBank": true,
            "Type": "3",
            "IsDeleted": false,
            "ModifiedDate": "2022-01-03T00:00:00"
        },
        {
            "ChartOfAccountID": "01139",
            "CompanyID": "011",
            "GroupAccountID": "01000001",
            "AccountNo": "1102009",
            "Description": "BNI - 8898820228",
            "ParentID": "01130",
            "IsChildest": true,
            "IsBank": true,
            "Type": "3",
            "IsDeleted": false,
            "ModifiedDate": "2022-01-03T00:00:00"
        },
        {
            "ChartOfAccountID": "01141",
            "CompanyID": "011",
            "GroupAccountID": "01000003",
            "AccountNo": "1103001",
            "Description": "Account Receivable",
            "ParentID": "01140",
            "IsChildest": true,
            "IsBank": false,
            "Type": "3",
            "IsDeleted": false,
            "ModifiedDate": "2022-01-03T00:00:00"
        },
        {
            "ChartOfAccountID": "01142",
            "CompanyID": "011",
            "GroupAccountID": "01000003",
            "AccountNo": "1103002",
            "Description": "Account Receivable USD",
            "ParentID": "01140",
            "IsChildest": true,
            "IsBank": false,
            "Type": "3",
            "IsDeleted": false,
            "ModifiedDate": "2022-01-03T00:00:00"
        },
        {
            "ChartOfAccountID": "01143",
            "CompanyID": "011",
            "GroupAccountID": "01000003",
            "AccountNo": "1103003",
            "Description": "Account Receivable EUR",
            "ParentID": "01140",
            "IsChildest": true,
            "IsBank": false,
            "Type": "3",
            "IsDeleted": false,
            "ModifiedDate": "2022-01-03T00:00:00"
        },
        {
            "ChartOfAccountID": "01144",
            "CompanyID": "011",
            "GroupAccountID": "01000003",
            "AccountNo": "110302",
            "Description": "Account Receivable IDR",
            "ParentID": "01140",
            "IsChildest": true,
            "IsBank": false,
            "Type": "3",
            "IsDeleted": false,
            "ModifiedDate": "2022-01-03T00:00:00"
        },
        {
            "ChartOfAccountID": "01146",
            "CompanyID": "011",
            "GroupAccountID": "01000005",
            "AccountNo": "1104001",
            "Description": "Advance Purchase",
            "ParentID": "01145",
            "IsChildest": true,
            "IsBank": false,
            "Type": "3",
            "IsDeleted": false,
            "ModifiedDate": "2022-01-03T00:00:00"
        },
        {
            "ChartOfAccountID": "01147",
            "CompanyID": "011",
            "GroupAccountID": "01000005",
            "AccountNo": "1104002",
            "Description": "Advance Purchase USD",
            "ParentID": "01145",
            "IsChildest": true,
            "IsBank": false,
            "Type": "3",
            "IsDeleted": false,
            "ModifiedDate": "2022-01-03T00:00:00"
        },
        {
            "ChartOfAccountID": "01148",
            "CompanyID": "011",
            "GroupAccountID": "01000005",
            "AccountNo": "1104003",
            "Description": "Advance Purchase EUR",
            "ParentID": "01145",
            "IsChildest": true,
            "IsBank": false,
            "Type": "3",
            "IsDeleted": false,
            "ModifiedDate": "2022-01-03T00:00:00"
        },
        {
            "ChartOfAccountID": "01149",
            "CompanyID": "011",
            "GroupAccountID": "01000005",
            "AccountNo": "110402",
            "Description": "Advance Purchase IDR",
            "ParentID": "01145",
            "IsChildest": true,
            "IsBank": false,
            "Type": "3",
            "IsDeleted": false,
            "ModifiedDate": "2022-01-03T00:00:00"
        },
        {
            "ChartOfAccountID": "01151",
            "CompanyID": "011",
            "GroupAccountID": "01000004",
            "AccountNo": "1105001",
            "Description": "Inventory Store",
            "ParentID": "01150",
            "IsChildest": true,
            "IsBank": false,
            "Type": "3",
            "IsDeleted": false,
            "ModifiedDate": "2022-01-03T00:00:00"
        },
        {
            "ChartOfAccountID": "01152",
            "CompanyID": "011",
            "GroupAccountID": "01000004",
            "AccountNo": "1105002",
            "Description": "Good in Transit",
            "ParentID": "01150",
            "IsChildest": true,
            "IsBank": false,
            "Type": "3",
            "IsDeleted": false,
            "ModifiedDate": "2022-01-03T00:00:00"
        },
        {
            "ChartOfAccountID": "01154",
            "CompanyID": "011",
            "GroupAccountID": "01000004",
            "AccountNo": "1106001",
            "Description": "Store Supplies",
            "ParentID": "01153",
            "IsChildest": true,
            "IsBank": false,
            "Type": "3",
            "IsDeleted": false,
            "ModifiedDate": "2022-01-03T00:00:00"
        },
        {
            "ChartOfAccountID": "01155",
            "CompanyID": "011",
            "GroupAccountID": "01000004",
            "AccountNo": "1106002",
            "Description": "Seragam&Sepatu",
            "ParentID": "01153",
            "IsChildest": true,
            "IsBank": false,
            "Type": "3",
            "IsDeleted": false,
            "ModifiedDate": "2022-01-03T00:00:00"
        },
        {
            "ChartOfAccountID": "01156",
            "CompanyID": "011",
            "GroupAccountID": "01000004",
            "AccountNo": "1106003",
            "Description": "Tissue dan Sisir",
            "ParentID": "01153",
            "IsChildest": true,
            "IsBank": false,
            "Type": "3",
            "IsDeleted": false,
            "ModifiedDate": "2022-01-03T00:00:00"
        },
        {
            "ChartOfAccountID": "01157",
            "CompanyID": "011",
            "GroupAccountID": "01000004",
            "AccountNo": "1106004",
            "Description": "Klipper & Tools",
            "ParentID": "01153",
            "IsChildest": true,
            "IsBank": false,
            "Type": "3",
            "IsDeleted": false,
            "ModifiedDate": "2022-01-03T00:00:00"
        },
        {
            "ChartOfAccountID": "01158",
            "CompanyID": "011",
            "GroupAccountID": "01000004",
            "AccountNo": "1106005",
            "Description": "Gel & Bedak",
            "ParentID": "01153",
            "IsChildest": true,
            "IsBank": false,
            "Type": "3",
            "IsDeleted": false,
            "ModifiedDate": "2022-01-03T00:00:00"
        },
        {
            "ChartOfAccountID": "01160",
            "CompanyID": "011",
            "GroupAccountID": "01000005",
            "AccountNo": "1107001",
            "Description": "Prepaid Rent",
            "ParentID": "01159",
            "IsChildest": true,
            "IsBank": false,
            "Type": "3",
            "IsDeleted": false,
            "ModifiedDate": "2022-01-03T00:00:00"
        },
        {
            "ChartOfAccountID": "01161",
            "CompanyID": "011",
            "GroupAccountID": "01000005",
            "AccountNo": "1107002",
            "Description": "Prepaid Insurance",
            "ParentID": "01159",
            "IsChildest": true,
            "IsBank": false,
            "Type": "3",
            "IsDeleted": false,
            "ModifiedDate": "2022-01-03T00:00:00"
        },
        {
            "ChartOfAccountID": "01162",
            "CompanyID": "011",
            "GroupAccountID": "01000005",
            "AccountNo": "1107003",
            "Description": "Other Prepaid",
            "ParentID": "01159",
            "IsChildest": true,
            "IsBank": false,
            "Type": "3",
            "IsDeleted": false,
            "ModifiedDate": "2022-01-03T00:00:00"
        },
        {
            "ChartOfAccountID": "01163",
            "CompanyID": "011",
            "GroupAccountID": "01000005",
            "AccountNo": "1107004",
            "Description": "Other Receivable",
            "ParentID": "01159",
            "IsChildest": true,
            "IsBank": false,
            "Type": "3",
            "IsDeleted": false,
            "ModifiedDate": "2022-01-03T00:00:00"
        },
        {
            "ChartOfAccountID": "01164",
            "CompanyID": "011",
            "GroupAccountID": "01000005",
            "AccountNo": "1107005",
            "Description": "Securities Deposit",
            "ParentID": "01159",
            "IsChildest": true,
            "IsBank": false,
            "Type": "3",
            "IsDeleted": false,
            "ModifiedDate": "2022-01-03T00:00:00"
        },
        {
            "ChartOfAccountID": "01166",
            "CompanyID": "011",
            "GroupAccountID": "01000005",
            "AccountNo": "1108001",
            "Description": "Prepaid Taxes VAT In",
            "ParentID": "01165",
            "IsChildest": true,
            "IsBank": false,
            "Type": "3",
            "IsDeleted": false,
            "ModifiedDate": "2022-01-03T00:00:00"
        },
        {
            "ChartOfAccountID": "01167",
            "CompanyID": "011",
            "GroupAccountID": "01000005",
            "AccountNo": "1108002",
            "Description": "Prepaid Taxes-Art 22",
            "ParentID": "01165",
            "IsChildest": true,
            "IsBank": false,
            "Type": "3",
            "IsDeleted": false,
            "ModifiedDate": "2022-01-03T00:00:00"
        },
        {
            "ChartOfAccountID": "01168",
            "CompanyID": "011",
            "GroupAccountID": "01000005",
            "AccountNo": "1108003",
            "Description": "Prepaid Taxes Art-23",
            "ParentID": "01165",
            "IsChildest": true,
            "IsBank": false,
            "Type": "3",
            "IsDeleted": false,
            "ModifiedDate": "2022-01-03T00:00:00"
        },
        {
            "ChartOfAccountID": "01169",
            "CompanyID": "011",
            "GroupAccountID": "01000005",
            "AccountNo": "1108004",
            "Description": "Prepaid Taxes Art-25",
            "ParentID": "01165",
            "IsChildest": true,
            "IsBank": false,
            "Type": "3",
            "IsDeleted": false,
            "ModifiedDate": "2022-01-03T00:00:00"
        },
        {
            "ChartOfAccountID": "01171",
            "CompanyID": "011",
            "GroupAccountID": "01000001",
            "AccountNo": "1110001",
            "Description": "Cross Account",
            "ParentID": "01170",
            "IsChildest": true,
            "IsBank": false,
            "Type": "3",
            "IsDeleted": false,
            "ModifiedDate": "2022-01-03T00:00:00"
        },
        {
            "ChartOfAccountID": "01172",
            "CompanyID": "011",
            "GroupAccountID": "01000001",
            "AccountNo": "1110002",
            "Description": "Fix Asset Transaction",
            "ParentID": "01170",
            "IsChildest": true,
            "IsBank": false,
            "Type": "3",
            "IsDeleted": false,
            "ModifiedDate": "2022-01-03T00:00:00"
        },
        {
            "ChartOfAccountID": "01173",
            "CompanyID": "011",
            "GroupAccountID": "01000001",
            "AccountNo": "1110003",
            "Description": "Cash Cross Acc Vending Mesin",
            "ParentID": "01170",
            "IsChildest": true,
            "IsBank": false,
            "Type": "3",
            "IsDeleted": false,
            "ModifiedDate": "2022-01-03T00:00:00"
        },
        {
            "ChartOfAccountID": "01129",
            "CompanyID": "011",
            "GroupAccountID": "01000001",
            "AccountNo": "1110016",
            "Description": "Cash - Office",
            "ParentID": "011",
            "IsChildest": true,
            "IsBank": true,
            "Type": "3",
            "IsDeleted": false,
            "ModifiedDate": "2022-01-03T00:00:00"
        },
        {
            "ChartOfAccountID": "01174",
            "CompanyID": "011",
            "GroupAccountID": "01000001",
            "AccountNo": "1110999",
            "Description": "Cash Reimbustment",
            "ParentID": "01170",
            "IsChildest": true,
            "IsBank": false,
            "Type": "3",
            "IsDeleted": false,
            "ModifiedDate": "2022-01-03T00:00:00"
        },
        {
            "ChartOfAccountID": "01198",
            "CompanyID": "011",
            "GroupAccountID": "01000003",
            "AccountNo": "1112001",
            "Description": "Employee Receivables",
            "ParentID": "01197",
            "IsChildest": true,
            "IsBank": false,
            "Type": "3",
            "IsDeleted": false,
            "ModifiedDate": "2022-01-03T00:00:00"
        },
        {
            "ChartOfAccountID": "01199",
            "CompanyID": "011",
            "GroupAccountID": "01000003",
            "AccountNo": "1112002",
            "Description": "Shareholder Receivables",
            "ParentID": "01197",
            "IsChildest": true,
            "IsBank": false,
            "Type": "3",
            "IsDeleted": false,
            "ModifiedDate": "2022-01-03T00:00:00"
        },
        {
            "ChartOfAccountID": "01200",
            "CompanyID": "011",
            "GroupAccountID": "01000003",
            "AccountNo": "1112003",
            "Description": "Other Receivables - Slip On",
            "ParentID": "01197",
            "IsChildest": true,
            "IsBank": false,
            "Type": "3",
            "IsDeleted": false,
            "ModifiedDate": "2022-01-03T00:00:00"
        },
        {
            "ChartOfAccountID": "01201",
            "CompanyID": "011",
            "GroupAccountID": "01000003",
            "AccountNo": "1112004",
            "Description": "Due to PT. IMA",
            "ParentID": "01197",
            "IsChildest": true,
            "IsBank": false,
            "Type": "3",
            "IsDeleted": false,
            "ModifiedDate": "2022-02-02T11:52:25.773"
        },
        {
            "ChartOfAccountID": "01389",
            "CompanyID": "011",
            "GroupAccountID": "01000003",
            "AccountNo": "1112005",
            "Description": "Due From IMA",
            "ParentID": "01197",
            "IsChildest": true,
            "IsBank": false,
            "Type": "3",
            "IsDeleted": false,
            "ModifiedDate": "2022-02-02T11:52:23.13"
        },
        {
            "ChartOfAccountID": "01175",
            "CompanyID": "011",
            "GroupAccountID": "01000001",
            "AccountNo": "1119001",
            "Description": "Cash Cross Vending Mesin Emporium",
            "ParentID": "01170",
            "IsChildest": true,
            "IsBank": false,
            "Type": "3",
            "IsDeleted": false,
            "ModifiedDate": "2022-01-03T00:00:00"
        },
        {
            "ChartOfAccountID": "01176",
            "CompanyID": "011",
            "GroupAccountID": "01000001",
            "AccountNo": "1119002",
            "Description": "Cash Cross Vending Mesin Lebak Bulus",
            "ParentID": "01170",
            "IsChildest": true,
            "IsBank": false,
            "Type": "3",
            "IsDeleted": false,
            "ModifiedDate": "2022-01-03T00:00:00"
        },
        {
            "ChartOfAccountID": "01177",
            "CompanyID": "011",
            "GroupAccountID": "01000001",
            "AccountNo": "1119003",
            "Description": "Cash Cross Vending Mesin Pacific Palace Mall",
            "ParentID": "01170",
            "IsChildest": true,
            "IsBank": false,
            "Type": "3",
            "IsDeleted": false,
            "ModifiedDate": "2022-01-03T00:00:00"
        },
        {
            "ChartOfAccountID": "01178",
            "CompanyID": "011",
            "GroupAccountID": "01000001",
            "AccountNo": "1119004",
            "Description": "Cash Cross Vending Mesin Paris Van Java",
            "ParentID": "01170",
            "IsChildest": true,
            "IsBank": false,
            "Type": "3",
            "IsDeleted": false,
            "ModifiedDate": "2022-01-03T00:00:00"
        },
        {
            "ChartOfAccountID": "01179",
            "CompanyID": "011",
            "GroupAccountID": "01000001",
            "AccountNo": "1119005",
            "Description": "Cash Cross Vending Mesin Slipi",
            "ParentID": "01170",
            "IsChildest": true,
            "IsBank": false,
            "Type": "3",
            "IsDeleted": false,
            "ModifiedDate": "2022-01-03T00:00:00"
        },
        {
            "ChartOfAccountID": "01180",
            "CompanyID": "011",
            "GroupAccountID": "01000001",
            "AccountNo": "1119006",
            "Description": "Cash Cross Vending Mesin Sunter",
            "ParentID": "01170",
            "IsChildest": true,
            "IsBank": false,
            "Type": "3",
            "IsDeleted": false,
            "ModifiedDate": "2022-01-03T00:00:00"
        },
        {
            "ChartOfAccountID": "01181",
            "CompanyID": "011",
            "GroupAccountID": "01000001",
            "AccountNo": "1119007",
            "Description": "Cash Cross Vending Mesin Karawaci Supermall",
            "ParentID": "01170",
            "IsChildest": true,
            "IsBank": false,
            "Type": "3",
            "IsDeleted": false,
            "ModifiedDate": "2022-01-03T00:00:00"
        },
        {
            "ChartOfAccountID": "01182",
            "CompanyID": "011",
            "GroupAccountID": "01000001",
            "AccountNo": "1119008",
            "Description": "Cash Cross Vending Mesin Benhil",
            "ParentID": "01170",
            "IsChildest": true,
            "IsBank": false,
            "Type": "3",
            "IsDeleted": false,
            "ModifiedDate": "2022-01-03T00:00:00"
        },
        {
            "ChartOfAccountID": "01183",
            "CompanyID": "011",
            "GroupAccountID": "01000001",
            "AccountNo": "1119009",
            "Description": "Cash Cross Vending Mesin Gandaria City",
            "ParentID": "01170",
            "IsChildest": true,
            "IsBank": false,
            "Type": "3",
            "IsDeleted": false,
            "ModifiedDate": "2022-01-03T00:00:00"
        },
        {
            "ChartOfAccountID": "01184",
            "CompanyID": "011",
            "GroupAccountID": "01000001",
            "AccountNo": "1119010",
            "Description": "Cash Cross Vending Mesin Sumarecon Serpong",
            "ParentID": "01170",
            "IsChildest": true,
            "IsBank": false,
            "Type": "3",
            "IsDeleted": false,
            "ModifiedDate": "2022-01-03T00:00:00"
        },
        {
            "ChartOfAccountID": "01185",
            "CompanyID": "011",
            "GroupAccountID": "01000001",
            "AccountNo": "1119011",
            "Description": "Cash Cross Vending Mesin Goonting PV",
            "ParentID": "01170",
            "IsChildest": true,
            "IsBank": false,
            "Type": "3",
            "IsDeleted": false,
            "ModifiedDate": "2022-01-03T00:00:00"
        },
        {
            "ChartOfAccountID": "01186",
            "CompanyID": "011",
            "GroupAccountID": "01000001",
            "AccountNo": "1119012",
            "Description": "Cash Cross Vending Mesin Goonting Malibu",
            "ParentID": "01170",
            "IsChildest": true,
            "IsBank": false,
            "Type": "3",
            "IsDeleted": false,
            "ModifiedDate": "2022-01-03T00:00:00"
        },
        {
            "ChartOfAccountID": "01187",
            "CompanyID": "011",
            "GroupAccountID": "01000001",
            "AccountNo": "1119013",
            "Description": "Cash Cross Vending Mesin Mall Taman Palem",
            "ParentID": "01170",
            "IsChildest": true,
            "IsBank": false,
            "Type": "3",
            "IsDeleted": false,
            "ModifiedDate": "2022-01-03T00:00:00"
        },
        {
            "ChartOfAccountID": "01188",
            "CompanyID": "011",
            "GroupAccountID": "01000001",
            "AccountNo": "1119014",
            "Description": "Cash Cross Vending Mesin Margocity",
            "ParentID": "01170",
            "IsChildest": true,
            "IsBank": false,
            "Type": "3",
            "IsDeleted": false,
            "ModifiedDate": "2022-01-03T00:00:00"
        },
        {
            "ChartOfAccountID": "01189",
            "CompanyID": "011",
            "GroupAccountID": "01000001",
            "AccountNo": "1119015",
            "Description": "Cash Cross Vending Mesin SMB",
            "ParentID": "01170",
            "IsChildest": true,
            "IsBank": false,
            "Type": "3",
            "IsDeleted": false,
            "ModifiedDate": "2022-01-03T00:00:00"
        },
        {
            "ChartOfAccountID": "01190",
            "CompanyID": "011",
            "GroupAccountID": "01000001",
            "AccountNo": "1119016",
            "Description": "Cash Cross Vending Mesin MOI",
            "ParentID": "01170",
            "IsChildest": true,
            "IsBank": false,
            "Type": "3",
            "IsDeleted": false,
            "ModifiedDate": "2022-01-03T00:00:00"
        },
        {
            "ChartOfAccountID": "01191",
            "CompanyID": "011",
            "GroupAccountID": "01000001",
            "AccountNo": "1119017",
            "Description": "Cash Cross Vending Mesin Ambasador",
            "ParentID": "01170",
            "IsChildest": true,
            "IsBank": false,
            "Type": "3",
            "IsDeleted": false,
            "ModifiedDate": "2022-01-03T00:00:00"
        },
        {
            "ChartOfAccountID": "01192",
            "CompanyID": "011",
            "GroupAccountID": "01000001",
            "AccountNo": "1119018",
            "Description": "Cash Cross Vending Mesin Juanda",
            "ParentID": "01170",
            "IsChildest": true,
            "IsBank": false,
            "Type": "3",
            "IsDeleted": false,
            "ModifiedDate": "2022-01-03T00:00:00"
        },
        {
            "ChartOfAccountID": "01193",
            "CompanyID": "011",
            "GroupAccountID": "01000001",
            "AccountNo": "1119019",
            "Description": "Cash Cross Vending Mesin Semanggi",
            "ParentID": "01170",
            "IsChildest": true,
            "IsBank": false,
            "Type": "3",
            "IsDeleted": false,
            "ModifiedDate": "2022-01-03T00:00:00"
        },
        {
            "ChartOfAccountID": "01194",
            "CompanyID": "011",
            "GroupAccountID": "01000001",
            "AccountNo": "1119020",
            "Description": "Cash Cross Vending Mesin Gajah Mada",
            "ParentID": "01170",
            "IsChildest": true,
            "IsBank": false,
            "Type": "3",
            "IsDeleted": false,
            "ModifiedDate": "2022-01-03T00:00:00"
        },
        {
            "ChartOfAccountID": "01195",
            "CompanyID": "011",
            "GroupAccountID": "01000001",
            "AccountNo": "1119021",
            "Description": "Cash Cross Vending Mesin Bintaro",
            "ParentID": "01170",
            "IsChildest": true,
            "IsBank": false,
            "Type": "3",
            "IsDeleted": false,
            "ModifiedDate": "2022-01-03T00:00:00"
        },
        {
            "ChartOfAccountID": "01196",
            "CompanyID": "011",
            "GroupAccountID": "01000001",
            "AccountNo": "1119022",
            "Description": "Cash Cross Vending Mesin Gading Nias",
            "ParentID": "01170",
            "IsChildest": true,
            "IsBank": false,
            "Type": "3",
            "IsDeleted": false,
            "ModifiedDate": "2022-01-03T00:00:00"
        },
        {
            "ChartOfAccountID": "01203",
            "CompanyID": "011",
            "GroupAccountID": "01000007",
            "AccountNo": "1201001",
            "Description": "Land",
            "ParentID": "01202",
            "IsChildest": true,
            "IsBank": false,
            "Type": "3",
            "IsDeleted": false,
            "ModifiedDate": "2022-01-03T00:00:00"
        },
        {
            "ChartOfAccountID": "01209",
            "CompanyID": "011",
            "GroupAccountID": "01000008",
            "AccountNo": "1202001",
            "Description": "Accumulated Depr. Land",
            "ParentID": "01208",
            "IsChildest": true,
            "IsBank": false,
            "Type": "3",
            "IsDeleted": false,
            "ModifiedDate": "2022-01-03T00:00:00"
        },
        {
            "ChartOfAccountID": "01210",
            "CompanyID": "011",
            "GroupAccountID": "01000008",
            "AccountNo": "1202002",
            "Description": "Accumulated Depr. Salon Equipment",
            "ParentID": "01208",
            "IsChildest": true,
            "IsBank": false,
            "Type": "3",
            "IsDeleted": false,
            "ModifiedDate": "2022-01-03T00:00:00"
        },
        {
            "ChartOfAccountID": "01211",
            "CompanyID": "011",
            "GroupAccountID": "01000008",
            "AccountNo": "1202003",
            "Description": "Accumulated Depr Office Equipment",
            "ParentID": "01208",
            "IsChildest": true,
            "IsBank": false,
            "Type": "3",
            "IsDeleted": false,
            "ModifiedDate": "2022-01-03T00:00:00"
        },
        {
            "ChartOfAccountID": "01212",
            "CompanyID": "011",
            "GroupAccountID": "01000008",
            "AccountNo": "1202004",
            "Description": "Accumulated Depr Vechile",
            "ParentID": "01208",
            "IsChildest": true,
            "IsBank": false,
            "Type": "3",
            "IsDeleted": false,
            "ModifiedDate": "2022-01-03T00:00:00"
        },
        {
            "ChartOfAccountID": "01213",
            "CompanyID": "011",
            "GroupAccountID": "01000008",
            "AccountNo": "1202005",
            "Description": "Accumulated Depr Trade Mark",
            "ParentID": "01208",
            "IsChildest": true,
            "IsBank": false,
            "Type": "3",
            "IsDeleted": false,
            "ModifiedDate": "2022-01-03T00:00:00"
        },
        {
            "ChartOfAccountID": "01204",
            "CompanyID": "011",
            "GroupAccountID": "01000007",
            "AccountNo": "1700002",
            "Description": "Salon Equipment",
            "ParentID": "01202",
            "IsChildest": true,
            "IsBank": false,
            "Type": "3",
            "IsDeleted": false,
            "ModifiedDate": "2022-01-03T00:00:00"
        }
    ],
    "Meta": {
        "Pagination": {
            "From": 101,
            "To": 200,
            "CurrentPage": 2,
            "LastPage": 4,
            "TotalRecord": 352
        }
    },
    "Links": {
        "BaseUrl": "BaseURL"
    }
}